{
  "D00": {
    "worldIdea": "_NOT_SPECIFIED_"
  },
  "D01": {
    "worldIdea": "_NOT_SPECIFIED_"
  },
  "D02": {
    "worldIdea": "_NOT_SPECIFIED_"
  },
  "D03": {
    "worldIdea": "_NOT_SPECIFIED_"
  },
  "D04": {
    "worldIdea": "_NOT_SPECIFIED_"
  },
  "D05": {
    "worldIdea": "_NOT_SPECIFIED_"
  },
  "D06": {
    "worldIdea": "_NOT_SPECIFIED_"
  },
  "D07": {
    "worldIdea": "_NOT_SPECIFIED_"
  },
  "D08": {
    "worldIdea": "_NOT_SPECIFIED_"
  },
  "D09": {
    "worldIdea": "_NOT_SPECIFIED_"
  },
  "D10": {
    "worldIdea": "_NOT_SPECIFIED_"
  },
  "D11": {
    "worldIdea": "_NOT_SPECIFIED_"
  },
  "D12": {
    "worldIdea": "_NOT_SPECIFIED_"
  },
  "D13": {
    "worldIdea": "_NOT_SPECIFIED_"
  },
  "D14": {
    "worldIdea": "_NOT_SPECIFIED_"
  },
  "D15": {
    "worldIdea": "_NOT_SPECIFIED_"
  },
  "D16": {
    "worldIdea": "_NOT_SPECIFIED_"
  },
  "D17": {
    "worldIdea": "_NOT_SPECIFIED_"
  },
  "D18": {
    "worldIdea": "_NOT_SPECIFIED_"
  },
  "D20": {
    "worldIdea": "_NOT_SPECIFIED_"
  },
  "D21": {
    "worldIdea": "_NOT_SPECIFIED_"
  },
  "D22": {
    "worldIdea": "_NOT_SPECIFIED_"
  },
  "D23": {
    "worldIdea": "_NOT_SPECIFIED_"
  },
  "D24": {
    "worldIdea": "_NOT_SPECIFIED_"
  },
  "D25": {
    "worldIdea": "_NOT_SPECIFIED_"
  },
  "D26": {
    "worldIdea": "_NOT_SPECIFIED_"
  },
  "D27": {
    "worldIdea": "_NOT_SPECIFIED_"
  },
  "D28": {
    "worldIdea": "_NOT_SPECIFIED_"
  },
  "D29": {
    "worldIdea": "_NOT_SPECIFIED_"
  },
  "D30": {
    "worldIdea": "_NOT_SPECIFIED_"
  },
  "D31": {
    "worldIdea": "_NOT_SPECIFIED_"
  },
  "D32": {
    "worldIdea": "_NOT_SPECIFIED_"
  },
  "D33": {
    "worldIdea": "_NOT_SPECIFIED_"
  },
  "D34": {
    "worldIdea": "_NOT_SPECIFIED_"
  },
  "D35": {
    "worldIdea": "_NOT_SPECIFIED_"
  },
  "D36": {
    "worldIdea": "_NOT_SPECIFIED_"
  },
  "D37": {
    "worldIdea": "_NOT_SPECIFIED_"
  },
  "D38": {
    "worldIdea": "_NOT_SPECIFIED_"
  },
  "D39": {
    "worldIdea": "_NOT_SPECIFIED_"
  },
  "C01": {
    "worldIdea": "_NOT_SPECIFIED_"
  },
  "A00": {
    "worldIdea": "_NOT_SPECIFIED_"
  },
  "A01": {
    "worldIdea": "_NOT_SPECIFIED_"
  },
  "A02": {
    "worldIdea": "_NOT_SPECIFIED_"
  },
  "A03": {
    "worldIdea": "_NOT_SPECIFIED_"
  },
  "A04": {
    "worldIdea": "_NOT_SPECIFIED_"
  },
  "A05": {
    "worldIdea": "_NOT_SPECIFIED_"
  },
  "A06": {
    "worldIdea": "_NOT_SPECIFIED_"
  },
  "A07": {
    "worldIdea": "_NOT_SPECIFIED_"
  },
  "A08": {
    "worldIdea": "_NOT_SPECIFIED_"
  },
  "A09": {
    "worldIdea": "_NOT_SPECIFIED_"
  },
  "A10": {
    "worldIdea": "_NOT_SPECIFIED_"
  },
  "W00": {
    "worldIdea": "_NOT_SPECIFIED_"
  },
  "W01": {
    "worldIdea": "Modern"
  },
  "W02": {
    "worldIdea": "Fantasy"
  },
  "W03": {
    "worldIdea": "Chaos"
  },
  "W04": {
    "worldIdea": "Fantasy"
  },
  "W05": {
    "worldIdea": "_NOT_SPECIFIED_"
  },
  "W06": {
    "worldIdea": "Wild"
  },
  "W07": {
    "worldIdea": "Fantasy"
  },
  "W08": {
    "worldIdea": "Chaos"
  },
  "W09": {
    "worldIdea": "Modern"
  },
  "W10": {
    "worldIdea": "Science"
  },
  "W11": {
    "worldIdea": "Wild"
  },
  "W12": {
    "worldIdea": "Nostalgy"
  },
  "W13": {
    "worldIdea": "Science"
  },
  "W14": {
    "worldIdea": "_NOT_SPECIFIED_"
  },
  "W15": {
    "worldIdea": "Science"
  },
  "W16": {
    "worldIdea": "_NOT_SPECIFIED_"
  },
  "W17": {
    "worldIdea": "Nostalgy"
  },
  "W18": {
    "worldIdea": "Modern"
  },
  "W19": {
    "worldIdea": "Wild"
  },
  "W20": {
    "worldIdea": "_NOT_SPECIFIED_"
  }
}